aob/__init__.py
aob/main.py
aob/prompts/__init__.py
aob/prompts/generate_test.py
aob/prompts/prompt_templates.py
aob/prompts/simple_example.py
aob/prompts/sqlite_example.py
aob/prompts/transform_example.py
aob/setup.py
aob-0.2.10.dist-info/LICENSE.md
aob-0.2.10.dist-info/METADATA
aob-0.2.10.dist-info/WHEEL
aob-0.2.10.dist-info/entry_points.txt
aob-0.2.10.dist-info/RECORD
