Metadata-Version: 2.1
Name: aob
Version: 0.2.10
Summary: CLI tool for managing and running AO Applications
Author: Pratik
Author-email: pratik@arweave.org
Requires-Python: >=3.13,<4.0
Classifier: Programming Language :: Python :: 3
Classifier: Programming Language :: Python :: 3.13
Requires-Dist: anthropic (>=0.42.0,<0.43.0)
Requires-Dist: ell-ai[sqlite] (>=0.0.15,<0.0.16)
Requires-Dist: fastapi (>=0.115.6,<0.116.0)
Requires-Dist: httpx (==0.27.2)
Requires-Dist: openai (>=1.54.1,<2.0.0)
Requires-Dist: rich (>=13.9.3,<14.0.0)
Requires-Dist: ruff (>=0.7.2,<0.8.0)
Requires-Dist: setuptools (>=75.3.0,<76.0.0)
Requires-Dist: typer (>=0.12.5,<0.13.0)
Requires-Dist: uvicorn (>=0.34.0,<0.35.0)
Requires-Dist: watchfiles (>=1.0.3,<2.0.0)
